mybatis/__init__.py
mybatis/cache.py
mybatis/connection.py
mybatis/errors.py
mybatis/mapper_manager.py
mybatis/mybatis.py
test/__init__.py
test/test_cache.py
test/test_connection.py
test/test_db_rollback.py
test/test_db_rollback_postgresql.py
test/test_mapper_manager.py
test/test_mybatis.py
test/test_mybatis_decorator.py
test/test_mybatis_decorator_postgresql.py
test/test_mybatis_postgresql.py
test/test_mybatis_sqlite3.py
test/test_namespace.py
test/test_sql_injection.py
mybatis-0.0.17.dist-info/LICENSE
mybatis-0.0.17.dist-info/METADATA
mybatis-0.0.17.dist-info/WHEEL
mybatis-0.0.17.dist-info/top_level.txt
mybatis-0.0.17.dist-info/RECORD
