Metadata-Version: 2.1
Name: mybatis
Version: 0.0.17
Summary: A python ORM like mybatis.
Home-page: https://github.com/ralgond/mybatis-py
Author: Teng Huang
Author-email: ht201509@163.com
License: Apache-2.0
Classifier: Programming Language :: Python :: 3
Classifier: License :: OSI Approved :: Apache Software License
Classifier: Operating System :: OS Independent
Requires-Python: >=3.8
License-File: LICENSE
Requires-Dist: mysql-connector-python>=9.0.0
Requires-Dist: Pympler>=1.1
Requires-Dist: orjson>=3.10.12
Requires-Dist: psycopg2-binary>=2.9.10
